rbn/__init__.py
rbn/__main__.py
rbn/bands.py
rbn/listener.py
rbn/logging.py
rbn/telnet.py
rbn-0.1.0.dist-info/LICENSE
rbn-0.1.0.dist-info/WHEEL
rbn-0.1.0.dist-info/METADATA
rbn-0.1.0.dist-info/RECORD
