Metadata-Version: 2.1
Name: rbn
Version: 0.1.0
Summary: A Python library for consuming data from the Reverse Beacon Network in real time
License: GPLv3
Author: Evan Pratten
Author-email: ewpratten@gmail.com
Requires-Python: >=3.7,<4.0
Classifier: License :: Other/Proprietary License
Classifier: Programming Language :: Python :: 3
Classifier: Programming Language :: Python :: 3.7
Classifier: Programming Language :: Python :: 3.8
Classifier: Programming Language :: Python :: 3.9
Requires-Dist: asyncio (>=3.4.3,<4.0.0)
Requires-Dist: rich (>=9.9.0,<10.0.0)
Requires-Dist: telnetlib3 (>=1.0.3,<2.0.0)
